pulpo/__init__.py
pulpo/pulpo.py
pulpo/utils/__init__.py
pulpo/utils/bw_parser.py
pulpo/utils/converter.py
pulpo/utils/optimizer.py
pulpo/utils/saver.py
pulpo/utils/utils.py
pulpo/utils/uncertainty/monte_carlo.py
pulpo_dev-1.4.3.dist-info/licenses/LICENSE
tests/__init__.py
tests/rice_database.py
tests/sample_database.py
tests/test_functions.py
pulpo_dev-1.4.3.dist-info/METADATA
pulpo_dev-1.4.3.dist-info/WHEEL
pulpo_dev-1.4.3.dist-info/top_level.txt
pulpo_dev-1.4.3.dist-info/RECORD
