Metadata-Version: 2.4
Name: pulpo-dev
Version: 1.4.3
Summary: Pulpo package for optimization in LCI databases
Author-email: Fabian Lechtenberg <fabian.lechtenberg@chem.ethz.ch>
Maintainer-email: Fabian Lechtenberg <fabian.lechtenberg@chem.ethz.ch>
License-Expression: BSD-3-Clause
Project-URL: homepage, https://github.com/flechtenberg/pulpo
Project-URL: repository, https://github.com/flechtenberg/pulpo
Classifier: Programming Language :: Python :: 3
Classifier: Operating System :: OS Independent
Requires-Python: >=3.10
License-File: LICENSE
Requires-Dist: fs==2.4.16
Requires-Dist: pyomo<=6.5.0
Requires-Dist: highspy==1.8.0
Requires-Dist: ipython==8.14.0
Requires-Dist: jupyterlab
Requires-Dist: numpy<2.0.0
Requires-Dist: pandas
Requires-Dist: scipy<=1.14.1
Requires-Dist: tqdm
Requires-Dist: xlsxwriter
Requires-Dist: openpyxl
Provides-Extra: bw2
Requires-Dist: bw2calc<=1.8.2; extra == "bw2"
Requires-Dist: bw2data<=3.9.9; extra == "bw2"
Provides-Extra: bw25
Requires-Dist: bw2calc>=2.0.0; extra == "bw25"
Requires-Dist: bw2data>=4.0.0; extra == "bw25"
Dynamic: license-file
